{
  "timestamp": "2026-01-29T03:47:33.954Z",
  "reason": "compaction",
  "status": {
    "version": "2.0",
    "lastUpdated": "2026-01-29T03:46:36.342Z",
    "activeFeatures": [
      "ui-ux-enhancement"
    ],
    "primaryFeature": "ui-ux-enhancement",
    "features": {
      "ui-ux-enhancement": {
        "phase": "do",
        "planPath": "docs/01-plan/features/ui-ux-enhancement.plan.md",
        "designPath": "docs/02-design/features/ui-ux-enhancement.design.md",
        "createdAt": "2026-01-29",
        "updatedAt": "2026-01-29",
        "doCompleted": true
      }
    },
    "pipeline": {
      "currentPhase": 1,
      "level": "Dynamic",
      "phaseHistory": []
    },
    "session": {
      "startedAt": "2026-01-29T01:03:42.225Z",
      "onboardingCompleted": false,
      "lastActivity": "2026-01-29T03:46:36.342Z"
    },
    "history": []
  }
}